animus_sdk/__init__.py
animus_sdk/_version.py
animus_sdk/datasets.py
animus_sdk/errors.py
animus_sdk/experiments.py
animus_sdk/git.py
animus_sdk/http_client.py
animus_sdk/telemetry.py
animus_datalab-1.0.0.dist-info/METADATA
animus_datalab-1.0.0.dist-info/WHEEL
animus_datalab-1.0.0.dist-info/top_level.txt
animus_datalab-1.0.0.dist-info/RECORD
