Metadata-Version: 2.4
Name: animus-datalab
Version: 1.0.0
Summary: Animus DataLab Python SDK
Requires-Python: >=3.10
